{
  "x-lix-key": "lix_directory_descriptor",
  "x-lix-version": "1",
  "x-lix-primary-key": [
    "/id"
  ],
  "x-lix-unique": [
    [
      "/path"
    ]
  ],
  "x-lix-override-lixcols": {
    "lixcol_file_id": "\"lix\"",
    "lixcol_plugin_key": "\"lix\""
  },
  "type": "object",
  "properties": {
    "id": {
      "type": "string",
      "x-lix-default": "lix_uuid_v7()"
    },
    "path": {
      "type": "string",
      "pattern": "^/.*/$"
    },
    "parent_id": {
      "type": [
        "string",
        "null"
      ]
    },
    "name": {
      "type": [
        "string",
        "null"
      ]
    },
    "hidden": {
      "type": "boolean",
      "x-lix-default": "false"
    }
  },
  "required": [
    "id",
    "path"
  ],
  "additionalProperties": false
}
